pystark/__init__.py
pystark/client.py
pystark/config.py
pystark/console.py
pystark/data.py
pystark/logger.py
pystark/methods/__init__.py
pystark/methods/callback.py
pystark/methods/command.py
pystark/methods/inline.py
pystark/types/__init__.py
pystark/types/message.py
PyStark-0.1.1.dist-info/LICENSE
PyStark-0.1.1.dist-info/METADATA
PyStark-0.1.1.dist-info/NOTICE
PyStark-0.1.1.dist-info/WHEEL
PyStark-0.1.1.dist-info/dependency_links.txt
PyStark-0.1.1.dist-info/entry_points.txt
PyStark-0.1.1.dist-info/top_level.txt
PyStark-0.1.1.dist-info/RECORD
