Metadata-Version: 2.1
Name: PyStark
Version: 0.1.1
Summary: An incomplete add-on extension to Pyrogram for personal use.
Home-page: https://github.com/StarkBotsIndustries/PyStark
Author: StarkBotsIndustries
Author-email: starkbotsindustries@gmail.com
License: GPLv3+
Download-URL: https://github.com/StarkBotsIndustries/PyStark/releases/latest
Project-URL: Community, https://t.me/StarkBots
Project-URL: Support, https://t.me/StarkBotsChat
Keywords: telegram,bot,pyrogram,python
Platform: UNKNOWN
Classifier: Development Status :: 3 - Alpha
Classifier: Intended Audience :: Developers
Classifier: License :: OSI Approved :: GNU General Public License v3 or later (GPLv3+)
Classifier: Operating System :: OS Independent
Classifier: Programming Language :: Python :: 3
Classifier: Programming Language :: Python :: 3.6
Classifier: Programming Language :: Python :: 3.7
Classifier: Programming Language :: Python :: 3.8
Classifier: Programming Language :: Python :: 3.9
Classifier: Programming Language :: Python :: 3.10
Classifier: Natural Language :: English
Classifier: Topic :: Communications :: Chat
Classifier: Topic :: Education :: Testing
Classifier: Topic :: Software Development :: Libraries
Classifier: Topic :: Software Development :: Libraries :: Python Modules
Requires-Python: ~=3.6
License-File: LICENSE
License-File: NOTICE
Requires-Dist: pyrogram
Requires-Dist: pyromod
Requires-Dist: python-dotenv
Requires-Dist: pytz
Requires-Dist: redis
Requires-Dist: SQLAlchemy
Requires-Dist: TgCrypto
